[{"Tweet_Id":"1603805620897038353","Date":"2022-12-16","Time":"18:33:51","Tweet":"Fans in Qatar 🇶🇦  can't wait to see @stonebwoy on stage.  Today is gonna be 🔥🔥🔥🔥  From Ashaiman to the world. 🌎  #WorldCup2022 #FIFAWorldCup2022 #Africa #Stonebwoy #bhimnation #Ghana #GhanaMusic  https:\/\/t.co\/5lSGrUIKyF","Language":"en","Mentions":"[{'screen_name': 'stonebwoy', 'name': '1gad', 'id': '105137891'}]","Replies_Count":0,"Retweets_Count":0,"Likes_Count":7,"Hashtags":"['worldcup2022', 'fifaworldcup2022', 'africa', 'stonebwoy', 'bhimnation', 'ghana', 'ghanamusic']","Cashtags":[],"Link":"https:\/\/twitter.com\/AJEBILA\/status\/1603805620897038353","Country":"ghana"},{"Tweet_Id":"1603762382614024193","Date":"2022-12-16","Time":"15:42:03","Tweet":"Africa’s best XI of the 2022 FIFA World Cup 🌏🤩  #Qatar2022 #WorldCup #WorldCup2022 #Morocco #Ghana #Cameroon #ziyech #Ounahi #Aboubakar #DimaMaghrib #AtlasLions #Africa #Kudus #BlackStars #16December     https:\/\/t.co\/lwsBV1dg05","Language":"en","Mentions":"[]","Replies_Count":0,"Retweets_Count":4,"Likes_Count":12,"Hashtags":"['qatar2022', 'worldcup', 'worldcup2022', 'morocco', 'ghana', 'cameroon', 'ziyech', 'ounahi', 'aboubakar', 'dimamaghrib', 'atlaslions', 'africa', 'kudus', 'blackstars', '16december']","Cashtags":[],"Link":"https:\/\/twitter.com\/PanAfricaFooty\/status\/1603762382614024193","Country":"ghana"},{"Tweet_Id":"1603704408813862912","Date":"2022-12-16","Time":"11:51:41","Tweet":"Ghana FA have shortlisted former Chelsea Champions League winning coach, Thomas Tuchel for the vacant Black Stars coaching job following Otto Addo’s departure after the World Cup.   #Ghana #ghanaontrack #FIFAWorldCup #BlackStars #ChelseaFC #Qatar2022 #WorldcupQatar2022 #Africa  https:\/\/t.co\/M320zV11Mi","Language":"en","Mentions":"[]","Replies_Count":1,"Retweets_Count":2,"Likes_Count":9,"Hashtags":"['ghana', 'ghanaontrack', 'fifaworldcup', 'blackstars', 'chelseafc', 'qatar2022', 'worldcupqatar2022', 'africa']","Cashtags":[],"Link":"https:\/\/twitter.com\/PanAfricaFooty\/status\/1603704408813862912","Country":"ghana"},{"Tweet_Id":"1603679536683663361","Date":"2022-12-16","Time":"10:12:51","Tweet":"Flashback Friday 🤩  1996 Nigeria 🇳🇬 gold medal Olympics squad vs 2010 Ghana 🇬🇭World Cup quarterfinalists squad   Which team will win?  #Nigeria #Ghana #FIFAWorldCup #BlackStars #Olympics #WorldcupQatar2022 #soarsupereagles #Bringbackthelove #Qatar2022 #WorldCup2022 #Africa  https:\/\/t.co\/kSOEXtlBsh","Language":"en","Mentions":"[]","Replies_Count":0,"Retweets_Count":2,"Likes_Count":6,"Hashtags":"['nigeria', 'ghana', 'fifaworldcup', 'blackstars', 'olympics', 'worldcupqatar2022', 'soarsupereagles', 'bringbackthelove', 'qatar2022', 'worldcup2022', 'africa']","Cashtags":[],"Link":"https:\/\/twitter.com\/PanAfricaFooty\/status\/1603679536683663361","Country":"ghana"},{"Tweet_Id":"1603633653103616000","Date":"2022-12-16","Time":"07:10:31","Tweet":"Be smart to learn from the mistake of others. @Transfor108 @CaksusDas #anniversary #Kumasi #OseikromBronya #Friday #Qatar2022 #WorldCupFinal #tolerance #TrendingNow #trend #Ghana #fypシ #FYP  https:\/\/t.co\/557K2wwcxW","Language":"en","Mentions":"[{'screen_name': 'transfor108', 'name': 'transformations 108 foundation', 'id': '1049344932819943425'}, {'screen_name': 'caksusdas', 'name': 'jnana caksus das', 'id': '1050464185895870465'}]","Replies_Count":1,"Retweets_Count":4,"Likes_Count":8,"Hashtags":"['anniversary', 'kumasi', 'oseikrombronya', 'friday', 'qatar2022', 'worldcupfinal', 'tolerance', 'trendingnow', 'trend', 'ghana', 'fypシ', 'fyp']","Cashtags":[],"Link":"https:\/\/twitter.com\/Transfor108\/status\/1603633653103616000","Country":"ghana"},{"Tweet_Id":"1603552681565589505","Date":"2022-12-16","Time":"01:48:46","Tweet":"Respect is given where respect is due @duttypaul X @stonebwoy #WorldCup2022 #Qatar2022 #bhimnatives #loyalty #love #Respect #globalcitizen #ghana #africa #Jamaica  https:\/\/t.co\/nxL9XVTgRY","Language":"en","Mentions":"[{'screen_name': 'duttypaul', 'name': 'sean paul', 'id': '84094372'}, {'screen_name': 'stonebwoy', 'name': '1gad', 'id': '105137891'}]","Replies_Count":0,"Retweets_Count":6,"Likes_Count":26,"Hashtags":"['worldcup2022', 'qatar2022', 'bhimnatives', 'loyalty', 'love', 'respect', 'globalcitizen', 'ghana', 'africa', 'jamaica']","Cashtags":[],"Link":"https:\/\/twitter.com\/NicholaskofiCo4\/status\/1603552681565589505","Country":"ghana"}]