[{"Tweet_Id":"1599592666773491712","Date":"2022-12-05","Time":"03:33:05","Tweet":"Argentina siendo Argentina #Qatar2022 #FIFAWorldCup2022 #FIFAWorldCup #ArgentinavsAustralia   #SeleccionArgentina #Australia  https:\/\/t.co\/DKS6WoHzH3","Language":"es","Mentions":"[]","Replies_Count":0,"Retweets_Count":2,"Likes_Count":22,"Hashtags":"['qatar2022', 'fifaworldcup2022', 'fifaworldcup', 'argentinavsaustralia', 'seleccionargentina', 'australia']","Cashtags":[],"Link":"https:\/\/twitter.com\/Mactn9\/status\/1599592666773491712","Country":"australia"},{"Tweet_Id":"1599578459340419072","Date":"2022-12-05","Time":"02:36:38","Tweet":"#SeleccionArgentina | Los canticos de los hinchas argentinos, post triunfo contra #Australia y clasificación a los cuartos de final de #Qatar2022.    Vídeo de @clarincom  #CopaDelMundo #Futbol #Pasion #Scaloni #Messi #Scaloneta  https:\/\/t.co\/Zd4rnhEWAM","Language":"es","Mentions":"[{'screen_name': 'clarincom', 'name': 'clarín', 'id': '8105922'}]","Replies_Count":0,"Retweets_Count":6,"Likes_Count":8,"Hashtags":"['seleccionargentina', 'australia', 'qatar2022', 'copadelmundo', 'futbol', 'pasion', 'scaloni', 'messi', 'scaloneta']","Cashtags":[],"Link":"https:\/\/twitter.com\/Siemprelaliga2\/status\/1599578459340419072","Country":"australia"}]