{"id": 1596982653647220737, "conversation_id": "1596982653647220737", "created_at": "2022-11-27 22:41:49 Hora estándar romance", "date": "2022-11-27", "time": "22:41:49", "timezone": "+0100", "user_id": 1251947750272442372, "username": "loveworld_peopl", "name": "loveworld", "place": "", "tweet": "#BREAKING #HOLLAND #MOROCCO  #BELGIUM  🔴 HOLLAND :#VIDEO RIOTS BY MOROCCAN FANS HAVE SPREAD FROM BRUSSELS TO AMSTERDAM!   Morocco won against Belgium 2-0 at the World Cup today.  #BreakingNews #UltimaHora #Amsterdam #Holanda #Belgica #Marruecos #WorldCup2022 #Clashes  https://t.co/vd97cnqTSN", "language": "en", "mentions": [], "urls": [], "photos": [], "replies_count": 0, "retweets_count": 10, "likes_count": 16, "hashtags": ["breaking", "holland", "morocco", "belgium", "video", "breakingnews", "ultimahora", "amsterdam", "holanda", "belgica", "marruecos", "worldcup2022", "clashes"], "cashtags": [], "link": "https://twitter.com/LoveWorld_Peopl/status/1596982653647220737", "retweet": false, "quote_url": "", "video": 1, "thumbnail": "https://pbs.twimg.com/ext_tw_video_thumb/1596982593702055942/pu/img/7bqH3jsz6JwFzQWN.jpg", "near": "", "geo": "", "source": "", "user_rt_id": "", "user_rt": "", "retweet_id": "", "reply_to": [], "retweet_date": "", "translate": "", "trans_src": "", "trans_dest": ""}
{"id": 1596800536959123456, "conversation_id": "1596800536959123456", "created_at": "2022-11-27 10:38:09 Hora estándar romance", "date": "2022-11-27", "time": "10:38:09", "timezone": "+0100", "user_id": 52052800, "username": "drumaralqadri", "name": "Shaykh Dr Umar Al-Qadri", "place": "", "tweet": "The last few days there has been so much negativity regarding the #QatarWorldCup2022. I decided to travel myself to #Doha to witness what the fuss is all about. I’ll be supporting #Oranje during #Netherlands VS #Qatar. Looking forward to one day supporting #Ireland in FIFA WC.  https://t.co/k9FE69OglJ", "language": "en", "mentions": [], "urls": [], "photos": ["https://pbs.twimg.com/media/Fij5nunWAAEI6g-.jpg"], "replies_count": 9, "retweets_count": 0, "likes_count": 60, "hashtags": ["qatarworldcup2022", "doha", "oranje", "netherlands", "qatar", "ireland"], "cashtags": [], "link": "https://twitter.com/DrUmarAlQadri/status/1596800536959123456", "retweet": false, "quote_url": "", "video": 1, "thumbnail": "https://pbs.twimg.com/media/Fij5nunWAAEI6g-.jpg", "near": "", "geo": "", "source": "", "user_rt_id": "", "user_rt": "", "retweet_id": "", "reply_to": [], "retweet_date": "", "translate": "", "trans_src": "", "trans_dest": ""}
{"id": 1596774906892812289, "conversation_id": "1596774906892812289", "created_at": "2022-11-27 08:56:19 Hora estándar romance", "date": "2022-11-27", "time": "08:56:19", "timezone": "+0100", "user_id": 961996772141871104, "username": "netherlands1974", "name": "Holland74 🇳🇱", "place": "", "tweet": "In the #WorldCup74 second round match #Netherlands vs #EastGermany/#DDR it was #RobRensenbrink (15) who scored his first and only #goal of the tournament.  A great one!   #Holland #Oranje #football #soccer #FIFA #worldcup #mundial #goals #Qatar2022  https://t.co/lI1B81PqJK", "language": "en", "mentions": [], "urls": [], "photos": [], "replies_count": 2, "retweets_count": 2, "likes_count": 24, "hashtags": ["worldcup74", "netherlands", "eastgermany", "ddr", "robrensenbrink", "goal", "holland", "oranje", "football", "soccer", "fifa", "worldcup", "mundial", "goals", "qatar2022"], "cashtags": [], "link": "https://twitter.com/Netherlands1974/status/1596774906892812289", "retweet": false, "quote_url": "", "video": 1, "thumbnail": "https://pbs.twimg.com/ext_tw_video_thumb/1596774814781513728/pu/img/LznP5x-9cvNz3HvM.jpg", "near": "", "geo": "", "source": "", "user_rt_id": "", "user_rt": "", "retweet_id": "", "reply_to": [], "retweet_date": "", "translate": "", "trans_src": "", "trans_dest": ""}
{"id": 1596760750613491712, "conversation_id": "1596760750613491712", "created_at": "2022-11-27 08:00:03 Hora estándar romance", "date": "2022-11-27", "time": "08:00:03", "timezone": "+0100", "user_id": 284003990, "username": "fifamedia", "name": "FIFA Media", "place": "", "tweet": "Over three quarters of all people watching TV in the #Netherlands watched the @FIFAWorldCup tie between 🇳🇱 &amp; 🇪🇨 on Friday #Qatar2022   #FIFAWorldCup  https://t.co/rIR0X0hjCv", "language": "en", "mentions": [{"screen_name": "fifaworldcup", "name": "fifa world cup", "id": "138372303"}], "urls": [], "photos": ["https://pbs.twimg.com/media/FijVbxmWQAEWvsx.jpg"], "replies_count": 24, "retweets_count": 37, "likes_count": 352, "hashtags": ["netherlands", "qatar2022", "fifaworldcup"], "cashtags": [], "link": "https://twitter.com/fifamedia/status/1596760750613491712", "retweet": false, "quote_url": "", "video": 1, "thumbnail": "https://pbs.twimg.com/media/FijVbxmWQAEWvsx.jpg", "near": "", "geo": "", "source": "", "user_rt_id": "", "user_rt": "", "retweet_id": "", "reply_to": [], "retweet_date": "", "translate": "", "trans_src": "", "trans_dest": ""}
