[{"Tweet_Id":"1594825849211166722","Date":"2022-11-21","Time":"23:51:27","Tweet":"#WorldCup Plays for 4 games Nov 22  🇦🇷#Argentina @ 1.15 (2.35u) 🇩🇰#Denmark @ 1.59 (1.31u) 🇵🇱#Poland @ 3.09 (0.07u) 🇫🇷#France @ 1.25 (0.14u)  #WorldCup2022 Record: 2-2 +2.23u✅  Some value, some not so much  https:\/\/t.co\/VnCWcksTyW","Language":"en","Mentions":"[]","Replies_Count":0,"Retweets_Count":6,"Likes_Count":23,"Hashtags":"['worldcup', 'argentina', 'denmark', 'poland', 'france', 'worldcup2022']","Cashtags":[],"Link":"https:\/\/twitter.com\/hammeritbets\/status\/1594825849211166722","Country":"dinamarca"},{"Tweet_Id":"1594774587216388099","Date":"2022-11-21","Time":"20:27:45","Tweet":"Martin Braithwaite: ‘Denmark are serious contenders … we can do something special’.  Interview by @sidlowe  https:\/\/t.co\/HMdOmFHdtk #Denmark #Qatar2022","Language":"en","Mentions":"[{'screen_name': 'sidlowe', 'name': 'sid lowe', 'id': '108957853'}]","Replies_Count":1,"Retweets_Count":6,"Likes_Count":22,"Hashtags":"['denmark', 'qatar2022']","Cashtags":[],"Link":"https:\/\/twitter.com\/guardian_sport\/status\/1594774587216388099","Country":"dinamarca"},{"Tweet_Id":"1594713453130051586","Date":"2022-11-21","Time":"16:24:50","Tweet":"The Predictions are now open for #Denmark vs #Tunisia 🔥  Pick a side and predict now on Prosper 👇  &gt;  https:\/\/t.co\/biTshgnUEZ &lt;  #WorldCup2022  https:\/\/t.co\/ejzSXJADgq","Language":"en","Mentions":"[]","Replies_Count":6,"Retweets_Count":7,"Likes_Count":18,"Hashtags":"['denmark', 'tunisia', 'worldcup2022']","Cashtags":[],"Link":"https:\/\/twitter.com\/Prosperpredict\/status\/1594713453130051586","Country":"dinamarca"},{"Tweet_Id":"1594659955432472576","Date":"2022-11-21","Time":"12:52:15","Tweet":"#QatarWorldCup2022 : Karim Benzema, Sadio Mane and the curse of talismanic players France and Senegal will want to emulate #Denmark who were spurred by Eriksen’s absence #Qatar2022 #karimbenzema #sadiomane   https:\/\/t.co\/6BtkoOmAyh","Language":"en","Mentions":"[]","Replies_Count":1,"Retweets_Count":1,"Likes_Count":9,"Hashtags":"['qatarworldcup2022', 'denmark', 'qatar2022', 'karimbenzema', 'sadiomane']","Cashtags":[],"Link":"https:\/\/twitter.com\/gulf_news\/status\/1594659955432472576","Country":"dinamarca"}]