[{"Tweet_Id":"1599518157676290049","Date":"2022-12-04","Time":"22:37:01","Tweet":"PARTIDAZOS EN #Qatar2022 娥 Este lunes 05\/12 se juegan los octavos de final del mundial, y #Jap贸n  choca contra la #Croacia  de #LukaModri, mientras #Brasil ю, buscar谩 el triunfo ante #CoreaDelSur 梆. Juega tu mundial y gana .  Gana al estilo #Ovaci贸n en  @MeridianbetPE  https:\/\/t.co\/jbSkMqRKYy","Language":"es","Mentions":"[{'screen_name': 'meridianbetpe', 'name': 'meridianbetpe', 'id': '885205078562439168'}]","Replies_Count":0,"Retweets_Count":2,"Likes_Count":6,"Hashtags":"['qatar2022', 'jap贸n', 'croacia', 'lukamodri', 'brasil', 'coreadelsur', 'ovaci贸n']","Cashtags":[],"Link":"https:\/\/twitter.com\/ovacionweb\/status\/1599518157676290049","Country":"croacia"},{"Tweet_Id":"1599396220270616576","Date":"2022-12-04","Time":"14:32:28","Tweet":"#Qatar2022 #Japon  vs #Croacia  este tal vez sea uno de los partidos m谩s parejos de octavos de final. Para alargue o penales. Yo le pongo una fichita a los asi谩ticos.","Language":"es","Mentions":"[]","Replies_Count":3,"Retweets_Count":0,"Likes_Count":155,"Hashtags":"['qatar2022', 'japon', 'croacia']","Cashtags":[],"Link":"https:\/\/twitter.com\/magiandtarot\/status\/1599396220270616576","Country":"croacia"}]