{"id": 1598101657681805313, "conversation_id": "1598101657681805313", "created_at": "2022-12-01 00:48:21 Hora estándar romance", "date": "2022-12-01", "time": "00:48:21", "timezone": "+0100", "user_id": 961785238191001601, "username": "havolinedeport", "name": "Havoline Deportivo", "place": "", "tweet": "📄Emotiva carta de Hernán Galíndez, tras su participación con #LaTri en la #CopaMundialFIFA.  \"#ECU es mi País y siempre lo voy a defender con todo lo que tenga para hacerlo\", enfatizó el guardamenta de #Aucas, reciente campeón del fútbol ecuatoriano.  #FIFAWorldCup #Qatar2022  https://t.co/npz6ESdqrl", "language": "es", "mentions": [], "urls": [], "photos": ["https://pbs.twimg.com/media/Fi2YrcWXoAInzh-.jpg"], "replies_count": 0, "retweets_count": 1, "likes_count": 13, "hashtags": ["latri", "copamundialfifa", "ecu", "aucas", "fifaworldcup", "qatar2022"], "cashtags": [], "link": "https://twitter.com/havolinedeport/status/1598101657681805313", "retweet": false, "quote_url": "", "video": 1, "thumbnail": "https://pbs.twimg.com/media/Fi2YrcWXoAInzh-.jpg", "near": "", "geo": "", "source": "", "user_rt_id": "", "user_rt": "", "retweet_id": "", "reply_to": [], "retweet_date": "", "translate": "", "trans_src": "", "trans_dest": ""}
{"id": 1598093848588206083, "conversation_id": "1598093848588206083", "created_at": "2022-12-01 00:17:19 Hora estándar romance", "date": "2022-12-01", "time": "00:17:19", "timezone": "+0100", "user_id": 1345263941031702528, "username": "reddevilnacion", "name": "Nación Red Devil (Nueva Cuenta)", "place": "", "tweet": "🔴 DIRECTO! 👉  https://t.co/Yde1Teo9Lf  Prendemos muchachos! 🔥 Vuelve #NRDMundial con el repaso de la jornada y las pasadas 🧐  TEMAS 🟥 😟 #Ecuador y #México eliminados 🤝 #Argentina clasificado a 8vos ⚠️ Situación de #CostaRica y #Uruguay   #NacionRedDevil | #Qatar2022  https://t.co/UuSkI2AYF2", "language": "es", "mentions": [], "urls": ["https://youtu.be/dUCz3WQgecU"], "photos": ["https://pbs.twimg.com/media/Fi2R242XoAAroEx.jpg"], "replies_count": 1, "retweets_count": 1, "likes_count": 13, "hashtags": ["nrdmundial", "ecuador", "méxico", "argentina", "costarica", "uruguay", "nacionreddevil", "qatar2022"], "cashtags": [], "link": "https://twitter.com/reddevilnacion/status/1598093848588206083", "retweet": false, "quote_url": "", "video": 1, "thumbnail": "https://pbs.twimg.com/media/Fi2R242XoAAroEx.jpg", "near": "", "geo": "", "source": "", "user_rt_id": "", "user_rt": "", "retweet_id": "", "reply_to": [], "retweet_date": "", "translate": "", "trans_src": "", "trans_dest": ""}
{"id": 1598070762744983552, "conversation_id": "1598070762744983552", "created_at": "2022-11-30 22:45:35 Hora estándar romance", "date": "2022-11-30", "time": "22:45:35", "timezone": "+0100", "user_id": 1382528770687574017, "username": "pizarrasportsec", "name": "Pizarra Sports", "place": "", "tweet": "¡Calma, calma! 👍🏼  #HernanGalindez aclara que no se ha despedido de #LaTri tras su participación mundialista en #Qatar2022. Es decir, ya dependerá que el portero siga siendo convocado más adelante.  https://t.co/ybHeMJwGfc", "language": "es", "mentions": [], "urls": [], "photos": ["https://pbs.twimg.com/media/Fi1844bXgAgVsg_.jpg"], "replies_count": 0, "retweets_count": 7, "likes_count": 20, "hashtags": ["hernangalindez", "latri", "qatar2022"], "cashtags": [], "link": "https://twitter.com/pizarrasportsec/status/1598070762744983552", "retweet": false, "quote_url": "", "video": 1, "thumbnail": "https://pbs.twimg.com/media/Fi1844bXgAgVsg_.jpg", "near": "", "geo": "", "source": "", "user_rt_id": "", "user_rt": "", "retweet_id": "", "reply_to": [], "retweet_date": "", "translate": "", "trans_src": "", "trans_dest": ""}
{"id": 1598066163879383041, "conversation_id": "1598066163879383041", "created_at": "2022-11-30 22:27:18 Hora estándar romance", "date": "2022-11-30", "time": "22:27:18", "timezone": "+0100", "user_id": 390220919, "username": "marcadorec", "name": "Marcador", "place": "", "tweet": "#Qatar2022 I Selección de #Ecuador: Gustavo Alfaro y los ‘siete pecados capitales’ que cometió ante Senegal ➡  https://t.co/kCfYFfFipJ  https://t.co/AO0dAqHo6f", "language": "es", "mentions": [], "urls": ["https://bit.ly/3VsHrFq"], "photos": ["https://pbs.twimg.com/media/Fi14stUXgBIEi1B.jpg"], "replies_count": 2, "retweets_count": 16, "likes_count": 18, "hashtags": ["qatar2022", "ecuador"], "cashtags": [], "link": "https://twitter.com/marcadorec/status/1598066163879383041", "retweet": false, "quote_url": "", "video": 1, "thumbnail": "https://pbs.twimg.com/media/Fi14stUXgBIEi1B.jpg", "near": "", "geo": "", "source": "", "user_rt_id": "", "user_rt": "", "retweet_id": "", "reply_to": [], "retweet_date": "", "translate": "", "trans_src": "", "trans_dest": ""}
{"id": 1598051794055270401, "conversation_id": "1598051794055270401", "created_at": "2022-11-30 21:30:12 Hora estándar romance", "date": "2022-11-30", "time": "21:30:12", "timezone": "+0100", "user_id": 1051801902474821632, "username": "primicias", "name": "Primicias", "place": "", "tweet": "#Qatar2022 | Estas fueron las 5 derrotas más dolorosas en la historia de #LaTri. La última de ellas frente a #Senegal.  https://t.co/DQhbIubi6A  https://t.co/nJFeMqk0uA", "language": "es", "mentions": [], "urls": ["http://prim.ec/eZKA50LRoVM"], "photos": ["https://pbs.twimg.com/media/Fi1ro16WIAA698H.jpg"], "replies_count": 0, "retweets_count": 2, "likes_count": 6, "hashtags": ["qatar2022", "latri", "senegal"], "cashtags": [], "link": "https://twitter.com/Primicias/status/1598051794055270401", "retweet": false, "quote_url": "", "video": 1, "thumbnail": "https://pbs.twimg.com/media/Fi1ro16WIAA698H.jpg", "near": "", "geo": "", "source": "", "user_rt_id": "", "user_rt": "", "retweet_id": "", "reply_to": [], "retweet_date": "", "translate": "", "trans_src": "", "trans_dest": ""}
{"id": 1598044951450947602, "conversation_id": "1598044951450947602", "created_at": "2022-11-30 21:03:01 Hora estándar romance", "date": "2022-11-30", "time": "21:03:01", "timezone": "+0100", "user_id": 110823396, "username": "oteroluis12", "name": "Luis Alberto Otero H ☮️", "place": "", "tweet": "Salvo que se haya quebrado algo internamente, cosa que sabemos que sí desde el día de la convocatoria para #Qatar2022 y aunque los medios oficialistas desmintieron con lanza en mano, Miguel Ángel Ramírez me parece un gran PLAN B para @LaTri. El A1 debe ser Gustavo Alfaro.", "language": "es", "mentions": [{"screen_name": "latri", "name": "la tri 🇪🇨", "id": "1131208134977032193"}], "urls": [], "photos": [], "replies_count": 1, "retweets_count": 1, "likes_count": 6, "hashtags": ["qatar2022"], "cashtags": [], "link": "https://twitter.com/OteroLuis12/status/1598044951450947602", "retweet": false, "quote_url": "", "video": 0, "thumbnail": "", "near": "", "geo": "", "source": "", "user_rt_id": "", "user_rt": "", "retweet_id": "", "reply_to": [], "retweet_date": "", "translate": "", "trans_src": "", "trans_dest": ""}
{"id": 1598036696431530000, "conversation_id": "1598036696431530000", "created_at": "2022-11-30 20:30:13 Hora estándar romance", "date": "2022-11-30", "time": "20:30:13", "timezone": "+0100", "user_id": 1051801902474821632, "username": "primicias", "name": "Primicias", "place": "", "tweet": "#Qatar2022 | Estos son los números de #LaTri en la #CopaMundialFIFA. Las estadísticas respaldan la buena actuación ecuatoriana.  https://t.co/NPKYro2Pyn", "language": "es", "mentions": [], "urls": ["http://prim.ec/VGIz50LRoQk"], "photos": [], "replies_count": 2, "retweets_count": 1, "likes_count": 7, "hashtags": ["qatar2022", "latri", "copamundialfifa"], "cashtags": [], "link": "https://twitter.com/Primicias/status/1598036696431530000", "retweet": false, "quote_url": "", "video": 0, "thumbnail": "", "near": "", "geo": "", "source": "", "user_rt_id": "", "user_rt": "", "retweet_id": "", "reply_to": [], "retweet_date": "", "translate": "", "trans_src": "", "trans_dest": ""}
{"id": 1598025224188231680, "conversation_id": "1598025224188231680", "created_at": "2022-11-30 19:44:37 Hora estándar romance", "date": "2022-11-30", "time": "19:44:37", "timezone": "+0100", "user_id": 961785238191001601, "username": "havolinedeport", "name": "Havoline Deportivo", "place": "", "tweet": "🚨👀\"Las sensaciones es que Alfaro no va a seguir y desde la #FEF se han puesto en contacto con Miguel Ángel Ramírez\"  #DeUna #ECU #LaTri #CopaMundialFIFA #FIFAWorldCup #Qatar2022  https://t.co/W4uXCTrl7K", "language": "es", "mentions": [], "urls": [], "photos": [], "replies_count": 0, "retweets_count": 3, "likes_count": 15, "hashtags": ["fef", "deuna", "ecu", "latri", "copamundialfifa", "fifaworldcup", "qatar2022"], "cashtags": [], "link": "https://twitter.com/havolinedeport/status/1598025224188231680", "retweet": false, "quote_url": "", "video": 1, "thumbnail": "https://pbs.twimg.com/ext_tw_video_thumb/1598025116465635330/pu/img/RzQDmdKflD4wuhbN.jpg", "near": "", "geo": "", "source": "", "user_rt_id": "", "user_rt": "", "retweet_id": "", "reply_to": [], "retweet_date": "", "translate": "", "trans_src": "", "trans_dest": ""}
{"id": 1598024035765735424, "conversation_id": "1598024035765735424", "created_at": "2022-11-30 19:39:54 Hora estándar romance", "date": "2022-11-30", "time": "19:39:54", "timezone": "+0100", "user_id": 961785238191001601, "username": "havolinedeport", "name": "Havoline Deportivo", "place": "", "tweet": "\"Yo siento que el ciclo está acabado. Le pediría al profe Alfaro, no se demore tanto en la decisión\"  #DeUna #ECU #LaTri #CopaMundialFIFA #FIFAWorldCup #Qatar2022  https://t.co/wjDs7CvuvW", "language": "es", "mentions": [], "urls": [], "photos": [], "replies_count": 0, "retweets_count": 2, "likes_count": 13, "hashtags": ["deuna", "ecu", "latri", "copamundialfifa", "fifaworldcup", "qatar2022"], "cashtags": [], "link": "https://twitter.com/havolinedeport/status/1598024035765735424", "retweet": false, "quote_url": "", "video": 1, "thumbnail": "https://pbs.twimg.com/ext_tw_video_thumb/1598023927028191241/pu/img/DyJM_LDVC0IDJCWs.jpg", "near": "", "geo": "", "source": "", "user_rt_id": "", "user_rt": "", "retweet_id": "", "reply_to": [], "retweet_date": "", "translate": "", "trans_src": "", "trans_dest": ""}
{"id": 1598017374636060672, "conversation_id": "1598017374636060672", "created_at": "2022-11-30 19:13:26 Hora estándar romance", "date": "2022-11-30", "time": "19:13:26", "timezone": "+0100", "user_id": 14333756, "username": "elcomerciocom", "name": "El Comercio", "place": "", "tweet": "#ConexiónMundial593 🇪🇨 | #Ecuador disputó tres partidos en #Qatar2022. ¿Cuántos jugadores no sumaron minutos? »  https://t.co/Gk4vVDR47R  https://t.co/JuTlCqG1he", "language": "es", "mentions": [], "urls": ["http://bit.ly/3Vm8FNA"], "photos": ["https://pbs.twimg.com/media/Fi1MHnIWAB4AjrE.jpg"], "replies_count": 0, "retweets_count": 6, "likes_count": 10, "hashtags": ["conexiónmundial593", "ecuador", "qatar2022"], "cashtags": [], "link": "https://twitter.com/elcomerciocom/status/1598017374636060672", "retweet": false, "quote_url": "", "video": 1, "thumbnail": "https://pbs.twimg.com/media/Fi1MHnIWAB4AjrE.jpg", "near": "", "geo": "", "source": "", "user_rt_id": "", "user_rt": "", "retweet_id": "", "reply_to": [], "retweet_date": "", "translate": "", "trans_src": "", "trans_dest": ""}
{"id": 1598014719410872320, "conversation_id": "1598014719410872320", "created_at": "2022-11-30 19:02:53 Hora estándar romance", "date": "2022-11-30", "time": "19:02:53", "timezone": "+0100", "user_id": 37717733, "username": "futbolecuador", "name": "futbolecuador.com", "place": "", "tweet": "¡#LaTri viaja de regreso a #Ecuador luego de quedar fuera del Mundial #Qatar2022! (VIDEO) La Selección Nacional ya abandona territorio qatarí al ser eliminada en la fase de grupos de #Qatar2022  https://t.co/3RlJRYfXr8  https://t.co/QNVJAGAYoe", "language": "es", "mentions": [], "urls": ["http://en.fut.ec/?l=151112"], "photos": ["https://pbs.twimg.com/media/Fi1J62wUUAcLkJB.jpg"], "replies_count": 0, "retweets_count": 0, "likes_count": 6, "hashtags": ["latri", "ecuador", "qatar2022", "qatar2022"], "cashtags": [], "link": "https://twitter.com/futbolecuador/status/1598014719410872320", "retweet": false, "quote_url": "", "video": 1, "thumbnail": "https://pbs.twimg.com/media/Fi1J62wUUAcLkJB.jpg", "near": "", "geo": "", "source": "", "user_rt_id": "", "user_rt": "", "retweet_id": "", "reply_to": [], "retweet_date": "", "translate": "", "trans_src": "", "trans_dest": ""}
{"id": 1598008860656156672, "conversation_id": "1598008860656156672", "created_at": "2022-11-30 18:39:36 Hora estándar romance", "date": "2022-11-30", "time": "18:39:36", "timezone": "+0100", "user_id": 1051801902474821632, "username": "primicias", "name": "Primicias", "place": "", "tweet": "#Qatar2022 | Desde este miércoles 30 de noviembre, Ecuador ha dejado de tener entrenador. ¿Cuáles son los escenarios de #LaTri con miras al próximo Mundial?  https://t.co/SoFKw6RBmQ  https://t.co/IQ1w96Kgls", "language": "es", "mentions": [], "urls": ["http://prim.ec/KufK50LRjES"], "photos": ["https://pbs.twimg.com/media/Fi1ElxuWAAABuL_.jpg"], "replies_count": 7, "retweets_count": 9, "likes_count": 18, "hashtags": ["qatar2022", "latri"], "cashtags": [], "link": "https://twitter.com/Primicias/status/1598008860656156672", "retweet": false, "quote_url": "", "video": 1, "thumbnail": "https://pbs.twimg.com/media/Fi1ElxuWAAABuL_.jpg", "near": "", "geo": "", "source": "", "user_rt_id": "", "user_rt": "", "retweet_id": "", "reply_to": [], "retweet_date": "", "translate": "", "trans_src": "", "trans_dest": ""}
{"id": 1598003521663946757, "conversation_id": "1598003521663946757", "created_at": "2022-11-30 18:18:23 Hora estándar romance", "date": "2022-11-30", "time": "18:18:23", "timezone": "+0100", "user_id": 256747696, "username": "ecuavisainforma", "name": "Ecuavisa Noticias", "place": "", "tweet": "😥 El plantel ecuatoriano partió de #Catar2022  y los jugadores toman rumbo a sus clubes. Ningún aficionado tricolor fue a despedir #LaTri.   Más detalles 👉  https://t.co/fghl6khCMy  https://t.co/0V6wc49WU4", "language": "es", "mentions": [], "urls": ["https://bit.ly/3ud1iw5"], "photos": ["https://pbs.twimg.com/media/Fi0-rGeWAAolxVe.jpg"], "replies_count": 12, "retweets_count": 9, "likes_count": 42, "hashtags": ["catar2022", "latri"], "cashtags": [], "link": "https://twitter.com/EcuavisaInforma/status/1598003521663946757", "retweet": false, "quote_url": "", "video": 1, "thumbnail": "https://pbs.twimg.com/media/Fi0-rGeWAAolxVe.jpg", "near": "", "geo": "", "source": "", "user_rt_id": "", "user_rt": "", "retweet_id": "", "reply_to": [], "retweet_date": "", "translate": "", "trans_src": "", "trans_dest": ""}
{"id": 1597998984366551040, "conversation_id": "1597998984366551040", "created_at": "2022-11-30 18:00:21 Hora estándar romance", "date": "2022-11-30", "time": "18:00:21", "timezone": "+0100", "user_id": 423574736, "username": "steevenmaciastv", "name": "Steeven Macías", "place": "", "tweet": "Que aburridos que se me hacen los partidos del #MundialQatar2022 ya sin #Ecuador . Veré sólo los de Brasil, Argentina, México, Portugal y España. Obviamente las semifinales y la final.", "language": "es", "mentions": [], "urls": [], "photos": [], "replies_count": 2, "retweets_count": 0, "likes_count": 10, "hashtags": ["mundialqatar2022", "ecuador"], "cashtags": [], "link": "https://twitter.com/steevenmaciastv/status/1597998984366551040", "retweet": false, "quote_url": "", "video": 0, "thumbnail": "", "near": "", "geo": "", "source": "", "user_rt_id": "", "user_rt": "", "retweet_id": "", "reply_to": [], "retweet_date": "", "translate": "", "trans_src": "", "trans_dest": ""}
{"id": 1597990489298698241, "conversation_id": "1597990489298698241", "created_at": "2022-11-30 17:26:36 Hora estándar romance", "date": "2022-11-30", "time": "17:26:36", "timezone": "+0100", "user_id": 111516761, "username": "naty_emelec", "name": "Naty Lo Azul", "place": "", "tweet": "Guerra Futbolística contra #Ecuador 😢 La #FIFA nos odia. 😭 #OrgullosamenteEcuatorianos  #EcuadorJuegaLimpio  #MundialQatar2022  https://t.co/M6YyOexgp9", "language": "es", "mentions": [], "urls": [], "photos": [], "replies_count": 1, "retweets_count": 9, "likes_count": 24, "hashtags": ["ecuador", "fifa", "orgullosamenteecuatorianos", "ecuadorjuegalimpio", "mundialqatar2022"], "cashtags": [], "link": "https://twitter.com/Naty_Emelec/status/1597990489298698241", "retweet": false, "quote_url": "", "video": 1, "thumbnail": "https://pbs.twimg.com/ext_tw_video_thumb/1597990449003757576/pu/img/U8pxgTSOrgHmFnW5.jpg", "near": "", "geo": "", "source": "", "user_rt_id": "", "user_rt": "", "retweet_id": "", "reply_to": [], "retweet_date": "", "translate": "", "trans_src": "", "trans_dest": ""}
{"id": 1597986653100199936, "conversation_id": "1597986653100199936", "created_at": "2022-11-30 17:11:21 Hora estándar romance", "date": "2022-11-30", "time": "17:11:21", "timezone": "+0100", "user_id": 1421133855793291270, "username": "marca90ec", "name": "Marca90Ec", "place": "", "tweet": "🟪 #5GYouTube HOY DESDE QATAR 🇶🇦  ⏰ 12h00 x YouTube   ¡Todo sobre la participación de #LaTri en la #FIFAworldcup2022 #Qatar2022   📲 Míralas Aquí:  https://t.co/6C0737GUTN   @mariegiselleca1 @sambaalvaradoc @jamolestina  https://t.co/hJz77dI00W", "language": "es", "mentions": [{"screen_name": "mariegiselleca1", "name": "mariegiselle carrillo areco", "id": "1177748193951567873"}, {"screen_name": "sambaalvaradoc", "name": "kristy alvarado c.", "id": "220946596"}, {"screen_name": "jamolestina", "name": "josé alberto molestina e.", "id": "142061797"}], "urls": ["https://youtu.be/dDvVd0_uyak"], "photos": ["https://pbs.twimg.com/media/Fi0wYjIXwAAoHLA.jpg"], "replies_count": 3, "retweets_count": 8, "likes_count": 16, "hashtags": ["5gyoutube", "latri", "fifaworldcup2022", "qatar2022"], "cashtags": [], "link": "https://twitter.com/marca90ec/status/1597986653100199936", "retweet": false, "quote_url": "", "video": 1, "thumbnail": "https://pbs.twimg.com/media/Fi0wYjIXwAAoHLA.jpg", "near": "", "geo": "", "source": "", "user_rt_id": "", "user_rt": "", "retweet_id": "", "reply_to": [], "retweet_date": "", "translate": "", "trans_src": "", "trans_dest": ""}
{"id": 1597983756522250243, "conversation_id": "1597983756522250243", "created_at": "2022-11-30 16:59:51 Hora estándar romance", "date": "2022-11-30", "time": "16:59:51", "timezone": "+0100", "user_id": 172498182, "username": "ramsses_mashi", "name": "Ramsses Torres", "place": "", "tweet": "¡GRACIAS! ECUADOR 🇪🇨 MI PAÍS | Nuestra selección nacional de fútbol ⚽️ tuvo una notable y decorosa participación en el Mundial de fútbol.| @FIFAcom en 🇶🇦 #Qatar2022    #LaTri    #OrgullosoNacional #HaremosHistoria @FEFecuador  #FIFAWorldCup  https://t.co/u0RAfYGCNI", "language": "es", "mentions": [{"screen_name": "fifacom", "name": "fifa.com", "id": "140070953"}, {"screen_name": "fefecuador", "name": "fef 🇪🇨", "id": "2409683900"}], "urls": [], "photos": [], "replies_count": 0, "retweets_count": 4, "likes_count": 11, "hashtags": ["qatar2022", "latri", "orgullosonacional", "haremoshistoria", "fifaworldcup"], "cashtags": [], "link": "https://twitter.com/RamssES_Mashi/status/1597983756522250243", "retweet": false, "quote_url": "", "video": 1, "thumbnail": "https://pbs.twimg.com/ext_tw_video_thumb/1597983632156663810/pu/img/n2MMK-AbsEfUptRM.jpg", "near": "", "geo": "", "source": "", "user_rt_id": "", "user_rt": "", "retweet_id": "", "reply_to": [], "retweet_date": "", "translate": "", "trans_src": "", "trans_dest": ""}
{"id": 1597979019156520963, "conversation_id": "1597979019156520963", "created_at": "2022-11-30 16:41:01 Hora estándar romance", "date": "2022-11-30", "time": "16:41:01", "timezone": "+0100", "user_id": 213720520, "username": "laredecuador", "name": "Radio La Red 102.1FM", "place": "", "tweet": "#VideosLaRed | Les compartimos las palabras del histórico Carlos Tenorio y su análisis del último compromiso de #LaTri en la Cita Mundialista de #Qatar2022.   #Catar2022EnLaRed #LaRadioQueSiempreEstá  https://t.co/Sf61V8n9uC", "language": "es", "mentions": [], "urls": [], "photos": [], "replies_count": 1, "retweets_count": 3, "likes_count": 15, "hashtags": ["videoslared", "latri", "qatar2022", "catar2022enlared", "laradioquesiempreestá"], "cashtags": [], "link": "https://twitter.com/LaRedEcuador/status/1597979019156520963", "retweet": false, "quote_url": "", "video": 1, "thumbnail": "https://pbs.twimg.com/ext_tw_video_thumb/1597978885404213255/pu/img/hU6m3YOeMeXMpPho.jpg", "near": "", "geo": "", "source": "", "user_rt_id": "", "user_rt": "", "retweet_id": "", "reply_to": [], "retweet_date": "", "translate": "", "trans_src": "", "trans_dest": ""}
{"id": 1597976198252212225, "conversation_id": "1597976198252212225", "created_at": "2022-11-30 16:29:49 Hora estándar romance", "date": "2022-11-30", "time": "16:29:49", "timezone": "+0100", "user_id": 14333756, "username": "elcomerciocom", "name": "El Comercio", "place": "", "tweet": "#ConexiónMundial593 🇪🇨 | #Ecuador no pasó de la fase de grupos en #Qatar2022 »  https://t.co/dv0jMGxkep  https://t.co/xL9RBdcZXh", "language": "es", "mentions": [], "urls": ["http://bit.ly/3BkQLmL"], "photos": ["https://pbs.twimg.com/media/Fi0m30ZXwAIRIZ3.jpg"], "replies_count": 0, "retweets_count": 14, "likes_count": 35, "hashtags": ["conexiónmundial593", "ecuador", "qatar2022"], "cashtags": [], "link": "https://twitter.com/elcomerciocom/status/1597976198252212225", "retweet": false, "quote_url": "", "video": 1, "thumbnail": "https://pbs.twimg.com/media/Fi0m30ZXwAIRIZ3.jpg", "near": "", "geo": "", "source": "", "user_rt_id": "", "user_rt": "", "retweet_id": "", "reply_to": [], "retweet_date": "", "translate": "", "trans_src": "", "trans_dest": ""}
{"id": 1597971539642966016, "conversation_id": "1597971539642966016", "created_at": "2022-11-30 16:11:18 Hora estándar romance", "date": "2022-11-30", "time": "16:11:18", "timezone": "+0100", "user_id": 256747696, "username": "ecuavisainforma", "name": "Ecuavisa Noticias", "place": "", "tweet": "#Qatar2022 | La despedida del Mundial deja muchas enseñanzas a los jugadores de 🇪🇨 #Ecuador, que tienen un promedio de 24 años.   Entérate cuáles son 👉  https://t.co/xncFHrr969  https://t.co/Lp9ZryfhTh", "language": "es", "mentions": [], "urls": ["https://bit.ly/3XMSfiY"], "photos": ["https://pbs.twimg.com/media/Fi0iIoiWAAAhvnH.jpg"], "replies_count": 1, "retweets_count": 2, "likes_count": 13, "hashtags": ["qatar2022", "ecuador"], "cashtags": [], "link": "https://twitter.com/EcuavisaInforma/status/1597971539642966016", "retweet": false, "quote_url": "", "video": 1, "thumbnail": "https://pbs.twimg.com/media/Fi0iIoiWAAAhvnH.jpg", "near": "", "geo": "", "source": "", "user_rt_id": "", "user_rt": "", "retweet_id": "", "reply_to": [], "retweet_date": "", "translate": "", "trans_src": "", "trans_dest": ""}
{"id": 1597969201142321154, "conversation_id": "1597969201142321154", "created_at": "2022-11-30 16:02:01 Hora estándar romance", "date": "2022-11-30", "time": "16:02:01", "timezone": "+0100", "user_id": 83983853, "username": "mauroascazubi", "name": "Mauro", "place": "", "tweet": "ÚLTIMO MINUTO. El presidente @LassoGuillermo anuncia la demolición de la casa de la selección.   Además añade una pregunta en la #ConsultaPopular que dice   ¿Está usted de acuerdo en que #LaTri pase a octavos de final del #MundialQatar2022 ?  ¡Tenemos presidente carajo!", "language": "es", "mentions": [{"screen_name": "lassoguillermo", "name": "guillermo lasso", "id": "300390462"}], "urls": [], "photos": [], "replies_count": 0, "retweets_count": 14, "likes_count": 40, "hashtags": ["consultapopular", "latri", "mundialqatar2022"], "cashtags": [], "link": "https://twitter.com/mauroascazubi/status/1597969201142321154", "retweet": false, "quote_url": "", "video": 0, "thumbnail": "", "near": "", "geo": "", "source": "", "user_rt_id": "", "user_rt": "", "retweet_id": "", "reply_to": [], "retweet_date": "", "translate": "", "trans_src": "", "trans_dest": ""}
{"id": 1597965989731528704, "conversation_id": "1597965989731528704", "created_at": "2022-11-30 15:49:15 Hora estándar romance", "date": "2022-11-30", "time": "15:49:15", "timezone": "+0100", "user_id": 312262343, "username": "borbsol", "name": "Sol Borja 🌺", "place": "", "tweet": "Cuando se admiran xq me gusta un montón el fútbol ⚽️ y lo veo, lo sigo, lo analizo, me gustaría poder contarles el porqué y son 👇🏼 razones como éstas las que lo hacen un deporte completo! #Qatar2022 #Humanidad #Respeto #Nobleza #Ecuador gracias por todo #LaTri  https://t.co/UbiCZMdXMG", "language": "es", "mentions": [], "urls": [], "photos": ["https://pbs.twimg.com/media/Fi0dmVAWYAEwnzM.jpg"], "replies_count": 0, "retweets_count": 2, "likes_count": 14, "hashtags": ["qatar2022", "humanidad", "respeto", "nobleza", "ecuador", "latri"], "cashtags": [], "link": "https://twitter.com/borbsol/status/1597965989731528704", "retweet": false, "quote_url": "", "video": 1, "thumbnail": "https://pbs.twimg.com/media/Fi0dmVAWYAEwnzM.jpg", "near": "", "geo": "", "source": "", "user_rt_id": "", "user_rt": "", "retweet_id": "", "reply_to": [], "retweet_date": "", "translate": "", "trans_src": "", "trans_dest": ""}
{"id": 1597960455812972544, "conversation_id": "1597960455812972544", "created_at": "2022-11-30 15:27:15 Hora estándar romance", "date": "2022-11-30", "time": "15:27:15", "timezone": "+0100", "user_id": 156173886, "username": "anamaroura", "name": "Ana María Roura", "place": "", "tweet": "Casi con unanimidad, lo que escucho de le gente de mi país #Ecuador 🇪🇨 hacia su selección es un gran « gracias » a pesar de no haber pasado a octavos de final en este #MundialQatar2022 Fueron alegría e ilusión para un país que atraviesa una de sus peores crisis de violencia. 🇪🇨🙏  https://t.co/GFUS5hjO4S", "language": "es", "mentions": [], "urls": [], "photos": ["https://pbs.twimg.com/media/Fi0YkFwWAAI68e8.jpg"], "replies_count": 0, "retweets_count": 3, "likes_count": 26, "hashtags": ["ecuador", "mundialqatar2022"], "cashtags": [], "link": "https://twitter.com/anamaroura/status/1597960455812972544", "retweet": false, "quote_url": "", "video": 1, "thumbnail": "https://pbs.twimg.com/media/Fi0YkFwWAAI68e8.jpg", "near": "", "geo": "", "source": "", "user_rt_id": "", "user_rt": "", "retweet_id": "", "reply_to": [], "retweet_date": "", "translate": "", "trans_src": "", "trans_dest": ""}
{"id": 1597946045123567617, "conversation_id": "1597946045123567617", "created_at": "2022-11-30 14:30:00 Hora estándar romance", "date": "2022-11-30", "time": "14:30:00", "timezone": "+0100", "user_id": 1283105062190030849, "username": "zoomecuador", "name": "Zoom Ec", "place": "", "tweet": "#URGENTE ¡PAOLA PABÓN SALUDA Y AGRADECE A LA TRI!  La Prefecta de Pichincha @PaolaPabonC envió un emotivo mensaje a #LaTri después de su gran participación en #WorldCup2022  “Dejaron todo en la cancha y les agradecemos de 💛💛💙❤️”  https://t.co/3RmWg590t4", "language": "es", "mentions": [{"screen_name": "paolapabonc", "name": "paola pabón", "id": "456186168"}], "urls": [], "photos": ["https://pbs.twimg.com/media/FiysmVcXoAEpySv.jpg"], "replies_count": 2, "retweets_count": 6, "likes_count": 17, "hashtags": ["urgente", "latri", "worldcup2022"], "cashtags": [], "link": "https://twitter.com/ZoomEcuador/status/1597946045123567617", "retweet": false, "quote_url": "", "video": 1, "thumbnail": "https://pbs.twimg.com/media/FiysmVcXoAEpySv.jpg", "near": "", "geo": "", "source": "", "user_rt_id": "", "user_rt": "", "retweet_id": "", "reply_to": [], "retweet_date": "", "translate": "", "trans_src": "", "trans_dest": ""}
{"id": 1597945703728291840, "conversation_id": "1597945703728291840", "created_at": "2022-11-30 14:28:38 Hora estándar romance", "date": "2022-11-30", "time": "14:28:38", "timezone": "+0100", "user_id": 1051801902474821632, "username": "primicias", "name": "Primicias", "place": "", "tweet": "#Qatar2022 | #LaTri abandonó Doha este miércoles 30 de noviembre. La idea era salir todos en un vuelo chárter, pero los planes de los jugadores cambió el operativo.  https://t.co/QwO7mnR0bP  https://t.co/MTEvjviv4N", "language": "es", "mentions": [], "urls": ["http://prim.ec/Ifr150LQYLa"], "photos": [], "replies_count": 2, "retweets_count": 9, "likes_count": 23, "hashtags": ["qatar2022", "latri"], "cashtags": [], "link": "https://twitter.com/Primicias/status/1597945703728291840", "retweet": false, "quote_url": "", "video": 1, "thumbnail": "https://pbs.twimg.com/ext_tw_video_thumb/1597945605296373761/pu/img/mh2Q2woNETkBuEXO.jpg", "near": "", "geo": "", "source": "", "user_rt_id": "", "user_rt": "", "retweet_id": "", "reply_to": [], "retweet_date": "", "translate": "", "trans_src": "", "trans_dest": ""}
{"id": 1597943771274137601, "conversation_id": "1597943771274137601", "created_at": "2022-11-30 14:20:58 Hora estándar romance", "date": "2022-11-30", "time": "14:20:58", "timezone": "+0100", "user_id": 111416958, "username": "espnargentina", "name": "ESPN Argentina", "place": "", "tweet": "#Video #ESPNQatarEnStarPlus No pudo ser para #Ecuador: el equipo de Alfaro necesitaba al menos empatar ante #Senegal pero cayó 2-1 y se quedó afuera de #Qatar2022.  https://t.co/QYWt35Lmm8", "language": "es", "mentions": [], "urls": ["https://www.espn.com.ar/video/clip/_/id/11299506?ex_cid=TW_FansAr"], "photos": [], "replies_count": 1, "retweets_count": 1, "likes_count": 7, "hashtags": ["video", "espnqatarenstarplus", "ecuador", "senegal", "qatar2022"], "cashtags": [], "link": "https://twitter.com/ESPNArgentina/status/1597943771274137601", "retweet": false, "quote_url": "", "video": 0, "thumbnail": "", "near": "", "geo": "", "source": "", "user_rt_id": "", "user_rt": "", "retweet_id": "", "reply_to": [], "retweet_date": "", "translate": "", "trans_src": "", "trans_dest": ""}
{"id": 1597942580313874432, "conversation_id": "1597942580313874432", "created_at": "2022-11-30 14:16:14 Hora estándar romance", "date": "2022-11-30", "time": "14:16:14", "timezone": "+0100", "user_id": 239508952, "username": "andresgregoriov", "name": "Andres Gregorio Vera", "place": "", "tweet": "Todo me recuerda a #Qatar2022   Dueles 😢 @LaTri  https://t.co/j9X5skP2W8", "language": "es", "mentions": [{"screen_name": "latri", "name": "la tri 🇪🇨", "id": "1131208134977032193"}], "urls": [], "photos": ["https://pbs.twimg.com/media/Fi0ISY6WQAILIFV.jpg", "https://pbs.twimg.com/tweet_video_thumb/Fi0ISY8WYAMd_tQ.jpg"], "replies_count": 0, "retweets_count": 0, "likes_count": 5, "hashtags": ["qatar2022"], "cashtags": [], "link": "https://twitter.com/andresgregorioV/status/1597942580313874432", "retweet": false, "quote_url": "", "video": 1, "thumbnail": "https://pbs.twimg.com/media/Fi0ISY6WQAILIFV.jpg", "near": "", "geo": "", "source": "", "user_rt_id": "", "user_rt": "", "retweet_id": "", "reply_to": [], "retweet_date": "", "translate": "", "trans_src": "", "trans_dest": ""}
{"id": 1597933507212345344, "conversation_id": "1597933507212345344", "created_at": "2022-11-30 13:40:10 Hora estándar romance", "date": "2022-11-30", "time": "13:40:10", "timezone": "+0100", "user_id": 1051801902474821632, "username": "primicias", "name": "Primicias", "place": "", "tweet": "#Qatar2022 | Los cerca de 7.000 hinchas que llegaron hasta Doha no se movieron de sus asientos. De alguna manera, acompañaron a los jugadores de #LaTri que seguían rendidos.  https://t.co/0dtUW2zerK", "language": "es", "mentions": [], "urls": ["http://prim.ec/LtLZ50LQRM3"], "photos": [], "replies_count": 1, "retweets_count": 2, "likes_count": 5, "hashtags": ["qatar2022", "latri"], "cashtags": [], "link": "https://twitter.com/Primicias/status/1597933507212345344", "retweet": false, "quote_url": "", "video": 0, "thumbnail": "", "near": "", "geo": "", "source": "", "user_rt_id": "", "user_rt": "", "retweet_id": "", "reply_to": [], "retweet_date": "", "translate": "", "trans_src": "", "trans_dest": ""}
{"id": 1597931641623777280, "conversation_id": "1597931641623777280", "created_at": "2022-11-30 13:32:46 Hora estándar romance", "date": "2022-11-30", "time": "13:32:46", "timezone": "+0100", "user_id": 181985096, "username": "diario_super", "name": "Diario Súper", "place": "", "tweet": "¡Miércoles de levantar la cabeza, mi Super📰 #Ecuador!  La portada en este 30/11 es un agradecimiento a #LaTri por esa participación mundialista que nos hizo emocionar. De #Qatar2022 estamos fuera, pero la ilusión por esta selección recién inicia  ¡Vuela a ver tu #DiarioFamiliar!  https://t.co/vIKtrGjXrG", "language": "es", "mentions": [], "urls": [], "photos": ["https://pbs.twimg.com/media/Fiz9UFUWYAEc-37.png"], "replies_count": 0, "retweets_count": 6, "likes_count": 11, "hashtags": ["ecuador", "latri", "qatar2022", "diariofamiliar"], "cashtags": [], "link": "https://twitter.com/Diario_Super/status/1597931641623777280", "retweet": false, "quote_url": "", "video": 1, "thumbnail": "https://pbs.twimg.com/media/Fiz9UFUWYAEc-37.png", "near": "", "geo": "", "source": "", "user_rt_id": "", "user_rt": "", "retweet_id": "", "reply_to": [], "retweet_date": "", "translate": "", "trans_src": "", "trans_dest": ""}
{"id": 1597917360010457088, "conversation_id": "1597917360010457088", "created_at": "2022-11-30 12:36:01 Hora estándar romance", "date": "2022-11-30", "time": "12:36:01", "timezone": "+0100", "user_id": 260284001, "username": "boletinerupcion", "name": "Boletín ERUPCIÓN", "place": "", "tweet": "En #Ambato y #Tungurahua aman a la selección y seleccionan su afectos ⚽️ #JavierAltamirano #ManuelCaizabanda #FernandoGavilanez #LaTri #Campana #Qatar2022  https://t.co/uzwpKeMpN8", "language": "es", "mentions": [], "urls": [], "photos": ["https://pbs.twimg.com/media/FizxXekXoAAZTof.jpg"], "replies_count": 0, "retweets_count": 0, "likes_count": 5, "hashtags": ["ambato", "tungurahua", "javieraltamirano", "manuelcaizabanda", "fernandogavilanez", "latri", "campana", "qatar2022"], "cashtags": [], "link": "https://twitter.com/boletinerupcion/status/1597917360010457088", "retweet": false, "quote_url": "", "video": 1, "thumbnail": "https://pbs.twimg.com/media/FizxXekXoAAZTof.jpg", "near": "", "geo": "", "source": "", "user_rt_id": "", "user_rt": "", "retweet_id": "", "reply_to": [], "retweet_date": "", "translate": "", "trans_src": "", "trans_dest": ""}
{"id": 1597913319004078082, "conversation_id": "1597913319004078082", "created_at": "2022-11-30 12:19:57 Hora estándar romance", "date": "2022-11-30", "time": "12:19:57", "timezone": "+0100", "user_id": 198960193, "username": "higuerahernan", "name": "Hernán Higuera", "place": "", "tweet": "“Lastimosamente, no hemos podido cumplir con las expectativas de nuestro Ecuador”, fueron las palabras de #EnnerValencia. #Ecuador #MundialQatar2022", "language": "es", "mentions": [], "urls": [], "photos": [], "replies_count": 1, "retweets_count": 1, "likes_count": 7, "hashtags": ["ennervalencia", "ecuador", "mundialqatar2022"], "cashtags": [], "link": "https://twitter.com/higuerahernan/status/1597913319004078082", "retweet": false, "quote_url": "https://twitter.com/EcuavisaInforma/status/1597757306111787008", "video": 0, "thumbnail": "", "near": "", "geo": "", "source": "", "user_rt_id": "", "user_rt": "", "retweet_id": "", "reply_to": [], "retweet_date": "", "translate": "", "trans_src": "", "trans_dest": ""}
{"id": 1597863092435750913, "conversation_id": "1597863092435750913", "created_at": "2022-11-30 09:00:22 Hora estándar romance", "date": "2022-11-30", "time": "09:00:22", "timezone": "+0100", "user_id": 876798176069656576, "username": "instinctfoot", "name": "Joana Swan ⚽ Instinct Foot", "place": "", "tweet": "Tenues locales pour la Cérémonie et le match d'ouverture de la coupe du monde 2022 au Qatar  #football #worldcup2022 #coupedumonde2022 #qatar #ecuador #Al BaytStadium  https://t.co/hIi9NKlLdW", "language": "fr", "mentions": [], "urls": [], "photos": ["https://pbs.twimg.com/media/FizABAMXgAUC5wU.jpg"], "replies_count": 1, "retweets_count": 0, "likes_count": 5, "hashtags": ["football", "worldcup2022", "coupedumonde2022", "qatar", "ecuador", "al"], "cashtags": [], "link": "https://twitter.com/instinctfoot/status/1597863092435750913", "retweet": false, "quote_url": "", "video": 1, "thumbnail": "https://pbs.twimg.com/media/FizABAMXgAUC5wU.jpg", "near": "", "geo": "", "source": "", "user_rt_id": "", "user_rt": "", "retweet_id": "", "reply_to": [], "retweet_date": "", "translate": "", "trans_src": "", "trans_dest": ""}
{"id": 1597861139446403073, "conversation_id": "1597861139446403073", "created_at": "2022-11-30 08:52:37 Hora estándar romance", "date": "2022-11-30", "time": "08:52:37", "timezone": "+0100", "user_id": 2847923049, "username": "freekick442", "name": "FreeKick442", "place": "", "tweet": "#Senegal became the first #African nation to qualify to the knock out stages of the #FIFAWorldCup2022 after beating #Ecuador 2:1. #freekick442, #Qatar2022  https://t.co/m4GjGsJXcq", "language": "en", "mentions": [], "urls": [], "photos": ["https://pbs.twimg.com/media/Fiy-OwXWYAEEZkG.jpg"], "replies_count": 0, "retweets_count": 2, "likes_count": 6, "hashtags": ["senegal", "african", "fifaworldcup2022", "ecuador", "freekick442", "qatar2022"], "cashtags": [], "link": "https://twitter.com/Freekick442/status/1597861139446403073", "retweet": false, "quote_url": "", "video": 1, "thumbnail": "https://pbs.twimg.com/media/Fiy-OwXWYAEEZkG.jpg", "near": "", "geo": "", "source": "", "user_rt_id": "", "user_rt": "", "retweet_id": "", "reply_to": [], "retweet_date": "", "translate": "", "trans_src": "", "trans_dest": ""}
{"id": 1597832862505525250, "conversation_id": "1597832862505525250", "created_at": "2022-11-30 07:00:15 Hora estándar romance", "date": "2022-11-30", "time": "07:00:15", "timezone": "+0100", "user_id": 876798176069656576, "username": "instinctfoot", "name": "Joana Swan ⚽ Instinct Foot", "place": "", "tweet": "Cérémonie et match d'ouverture de la coupe du monde 2022 au Qatar  #football #worldcup2022 #coupedumonde2022 #qatar #ecuador #Al BaytStadium  https://t.co/eUIhgqyOwl", "language": "fr", "mentions": [], "urls": [], "photos": ["https://pbs.twimg.com/media/FiykhYMXoAEslaO.jpg"], "replies_count": 0, "retweets_count": 0, "likes_count": 6, "hashtags": ["football", "worldcup2022", "coupedumonde2022", "qatar", "ecuador", "al"], "cashtags": [], "link": "https://twitter.com/instinctfoot/status/1597832862505525250", "retweet": false, "quote_url": "", "video": 1, "thumbnail": "https://pbs.twimg.com/media/FiykhYMXoAEslaO.jpg", "near": "", "geo": "", "source": "", "user_rt_id": "", "user_rt": "", "retweet_id": "", "reply_to": [], "retweet_date": "", "translate": "", "trans_src": "", "trans_dest": ""}
{"id": 1597830785662218240, "conversation_id": "1597830785662218240", "created_at": "2022-11-30 06:52:00 Hora estándar romance", "date": "2022-11-30", "time": "06:52:00", "timezone": "+0100", "user_id": 45013575, "username": "telesurtv", "name": "teleSUR TV", "place": "", "tweet": "#Ecuador🇪🇨perdió ante #Senegal🇸🇳con un marcado de 2-1 en la tercera fecha por la fase de grupos del Mundial de #Qatar2022,con lo cual la tricolor fue eliminada de la Copa del Mundo, mientras los \"Los Leones de Teranga\"se clasificaron a los octavos de final  https://t.co/FR4mleyfLF", "language": "es", "mentions": [], "urls": ["https://bit.ly/3inLpQU"], "photos": [], "replies_count": 0, "retweets_count": 5, "likes_count": 6, "hashtags": ["ecuador", "senegal", "qatar2022"], "cashtags": [], "link": "https://twitter.com/teleSURtv/status/1597830785662218240", "retweet": false, "quote_url": "", "video": 0, "thumbnail": "", "near": "", "geo": "", "source": "", "user_rt_id": "", "user_rt": "", "retweet_id": "", "reply_to": [], "retweet_date": "", "translate": "", "trans_src": "", "trans_dest": ""}
{"id": 1597815141541691392, "conversation_id": "1597815141541691392", "created_at": "2022-11-30 05:49:50 Hora estándar romance", "date": "2022-11-30", "time": "05:49:50", "timezone": "+0100", "user_id": 37717733, "username": "futbolecuador", "name": "futbolecuador.com", "place": "", "tweet": "\"Mantengan la humildad, la frente en alto y a seguir trabajando duro\". Antonio Valencia respaldó el proceso que defendió a #LaTri en #Qatar2022 con juventud  https://t.co/EUOePYuUnJ  https://t.co/eJdI6VyeJS", "language": "es", "mentions": [], "urls": ["http://en.fut.ec/?l=151100"], "photos": ["https://pbs.twimg.com/media/FiyUZ5XUUAAOklo.jpg"], "replies_count": 0, "retweets_count": 0, "likes_count": 12, "hashtags": ["latri", "qatar2022"], "cashtags": [], "link": "https://twitter.com/futbolecuador/status/1597815141541691392", "retweet": false, "quote_url": "", "video": 1, "thumbnail": "https://pbs.twimg.com/media/FiyUZ5XUUAAOklo.jpg", "near": "", "geo": "", "source": "", "user_rt_id": "", "user_rt": "", "retweet_id": "", "reply_to": [], "retweet_date": "", "translate": "", "trans_src": "", "trans_dest": ""}
{"id": 1597814165913370624, "conversation_id": "1597814165913370624", "created_at": "2022-11-30 05:45:57 Hora estándar romance", "date": "2022-11-30", "time": "05:45:57", "timezone": "+0100", "user_id": 1016724631074557953, "username": "ecpeloteros", "name": "Peloteros Ecuador", "place": "", "tweet": "Gustavo Alfaro post derrota ante Senegal dejó ‘en el aire’ su continuidad al mando de #LaTri, tras ser eliminados en la ‘puerta del horno’ de los octavos de final del Mundial #Qatar2022   Más detalles ➡️  https://t.co/pNM44eUzTc  https://t.co/rmVYzVyhFD", "language": "es", "mentions": [], "urls": ["https://bit.ly/3UimPy6"], "photos": ["https://pbs.twimg.com/media/FiySVstWQAYdAIv.jpg"], "replies_count": 0, "retweets_count": 5, "likes_count": 5, "hashtags": ["latri", "qatar2022"], "cashtags": [], "link": "https://twitter.com/EcPeloteros/status/1597814165913370624", "retweet": false, "quote_url": "", "video": 1, "thumbnail": "https://pbs.twimg.com/media/FiySVstWQAYdAIv.jpg", "near": "", "geo": "", "source": "", "user_rt_id": "", "user_rt": "", "retweet_id": "", "reply_to": [], "retweet_date": "", "translate": "", "trans_src": "", "trans_dest": ""}
{"id": 1597809952282013697, "conversation_id": "1597809952282013697", "created_at": "2022-11-30 05:29:13 Hora estándar romance", "date": "2022-11-30", "time": "05:29:13", "timezone": "+0100", "user_id": 449397239, "username": "wilsonmerinor", "name": "Wilson Merino Rivadeneira", "place": "", "tweet": ".@LaTri no es un suceso, es un proceso. Hay que sentirse muy orgullosos de lo alcanzado en el #MundialQatar2022 y apoyar a estos muchachos para que el día mañana sean los campeones del mundo. ¡Claro que es posible! ¡Sin miedo al futuro! 🚀  #VamosEcuador 💛💙❤️  https://t.co/Iz0cWkzrpA", "language": "es", "mentions": [{"screen_name": "latri", "name": "la tri 🇪🇨", "id": "1131208134977032193"}], "urls": [], "photos": ["https://pbs.twimg.com/media/FiyPrT7XEAANnkY.jpg"], "replies_count": 2, "retweets_count": 5, "likes_count": 43, "hashtags": ["mundialqatar2022", "vamosecuador"], "cashtags": [], "link": "https://twitter.com/WilsonMerinoR/status/1597809952282013697", "retweet": false, "quote_url": "", "video": 1, "thumbnail": "https://pbs.twimg.com/media/FiyPrT7XEAANnkY.jpg", "near": "", "geo": "", "source": "", "user_rt_id": "", "user_rt": "", "retweet_id": "", "reply_to": [], "retweet_date": "", "translate": "", "trans_src": "", "trans_dest": ""}
{"id": 1597803353610006531, "conversation_id": "1597803353610006531", "created_at": "2022-11-30 05:02:59 Hora estándar romance", "date": "2022-11-30", "time": "05:02:59", "timezone": "+0100", "user_id": 322202523, "username": "davidruiz28", "name": "David Ruiz 🇪🇨 🐍", "place": "", "tweet": "En vivo. 🔥🔥🔥🔥🔥🔥 #Qatar2022 #Ecuador", "language": "es", "mentions": [], "urls": [], "photos": [], "replies_count": 0, "retweets_count": 0, "likes_count": 7, "hashtags": ["qatar2022", "ecuador"], "cashtags": [], "link": "https://twitter.com/DavidRuiz28/status/1597803353610006531", "retweet": false, "quote_url": "https://twitter.com/FUTBOLTOTALEC1/status/1597803163314454528", "video": 0, "thumbnail": "", "near": "", "geo": "", "source": "", "user_rt_id": "", "user_rt": "", "retweet_id": "", "reply_to": [], "retweet_date": "", "translate": "", "trans_src": "", "trans_dest": ""}
{"id": 1597792658470363136, "conversation_id": "1597792658470363136", "created_at": "2022-11-30 04:20:29 Hora estándar romance", "date": "2022-11-30", "time": "04:20:29", "timezone": "+0100", "user_id": 1247583620543512578, "username": "outpapergye", "name": "Outpaper", "place": "", "tweet": "#PORTADAESPECIAL   GRACIAS  #mundial2022 #Ecuador #MundialQatar2022  https://t.co/f988NdUDJR", "language": "es", "mentions": [], "urls": [], "photos": ["https://pbs.twimg.com/media/Fix_9FnXkAELcmM.jpg"], "replies_count": 0, "retweets_count": 3, "likes_count": 6, "hashtags": ["portadaespecial", "mundial2022", "ecuador", "mundialqatar2022"], "cashtags": [], "link": "https://twitter.com/outpapergye/status/1597792658470363136", "retweet": false, "quote_url": "", "video": 1, "thumbnail": "https://pbs.twimg.com/media/Fix_9FnXkAELcmM.jpg", "near": "", "geo": "", "source": "", "user_rt_id": "", "user_rt": "", "retweet_id": "", "reply_to": [], "retweet_date": "", "translate": "", "trans_src": "", "trans_dest": ""}
{"id": 1597788043364438017, "conversation_id": "1597788043364438017", "created_at": "2022-11-30 04:02:09 Hora estándar romance", "date": "2022-11-30", "time": "04:02:09", "timezone": "+0100", "user_id": 822950666532515841, "username": "guaytamba_ldu", "name": "Guaytamba", "place": "", "tweet": "Veo los videos de @LaTri  y se me caen las lágrimas, pero al mismo tiempo feliz, porque nos hicieron pasar momentos de alegría en cada partido.  Gracias #Ecuador 🇪🇨♥️ #Qatar2022", "language": "es", "mentions": [{"screen_name": "latri", "name": "la tri 🇪🇨", "id": "1131208134977032193"}], "urls": [], "photos": [], "replies_count": 1, "retweets_count": 0, "likes_count": 24, "hashtags": ["ecuador", "qatar2022"], "cashtags": [], "link": "https://twitter.com/Guaytamba_LDU/status/1597788043364438017", "retweet": false, "quote_url": "", "video": 0, "thumbnail": "", "near": "", "geo": "", "source": "", "user_rt_id": "", "user_rt": "", "retweet_id": "", "reply_to": [], "retweet_date": "", "translate": "", "trans_src": "", "trans_dest": ""}
{"id": 1597787011842441217, "conversation_id": "1597787011842441217", "created_at": "2022-11-30 03:58:03 Hora estándar romance", "date": "2022-11-30", "time": "03:58:03", "timezone": "+0100", "user_id": 97513349, "username": "ecuavisa", "name": "Ecuavisa", "place": "", "tweet": "¡#LaTri llegó al final de su odisea mundialista! 🛳️  #Senegal 🇸🇳 logró ganar el partido contra la 'Tricolor', pasando a octavos de final de #Qatar2022.  Te contamos todo en #BitácoraQatar 📔.  Escúchanos ▶️  https://t.co/aLAnRFOkLI  https://t.co/8MQ1deZ8Iu", "language": "es", "mentions": [], "urls": ["https://spoti.fi/3EJbgu2"], "photos": [], "replies_count": 1, "retweets_count": 3, "likes_count": 7, "hashtags": ["latri", "senegal", "qatar2022", "bitácoraqatar"], "cashtags": [], "link": "https://twitter.com/ecuavisa/status/1597787011842441217", "retweet": false, "quote_url": "", "video": 1, "thumbnail": "https://pbs.twimg.com/ext_tw_video_thumb/1597786517216296960/pu/img/prpZZUqX_BskQlEz.jpg", "near": "", "geo": "", "source": "", "user_rt_id": "", "user_rt": "", "retweet_id": "", "reply_to": [], "retweet_date": "", "translate": "", "trans_src": "", "trans_dest": ""}
{"id": 1597784978473259009, "conversation_id": "1597784978473259009", "created_at": "2022-11-30 03:49:58 Hora estándar romance", "date": "2022-11-30", "time": "03:49:58", "timezone": "+0100", "user_id": 1004955393188081664, "username": "ecnop98", "name": "Ecnop 🇸🇻", "place": "", "tweet": "Arrancamos #Qatar2022 en #PES2021 Estaré jugando en el grupo A con #LaTri En vivo en mi canal por si quieres pasarte a ver y saludar en el vivo 💪🏼🏆  🔴YouTube:  https://t.co/gzEiGQkPuL  https://t.co/gzEiGQkPuL  https://t.co/mjJ083ACpk", "language": "es", "mentions": [], "urls": ["https://youtube.com/@ecnop9866", "https://youtube.com/@ecnop9866"], "photos": ["https://pbs.twimg.com/media/Fix4-BuX0AIuEvJ.jpg"], "replies_count": 0, "retweets_count": 4, "likes_count": 9, "hashtags": ["qatar2022", "pes2021", "latri"], "cashtags": [], "link": "https://twitter.com/Ecnop98/status/1597784978473259009", "retweet": false, "quote_url": "", "video": 1, "thumbnail": "https://pbs.twimg.com/media/Fix4-BuX0AIuEvJ.jpg", "near": "", "geo": "", "source": "", "user_rt_id": "", "user_rt": "", "retweet_id": "", "reply_to": [], "retweet_date": "", "translate": "", "trans_src": "", "trans_dest": ""}
{"id": 1597772388141531137, "conversation_id": "1597772388141531137", "created_at": "2022-11-30 02:59:57 Hora estándar romance", "date": "2022-11-30", "time": "02:59:57", "timezone": "+0100", "user_id": 139841110, "username": "michael_churos", "name": "Michael Arévalo Morán", "place": "", "tweet": "Gracias a @LaTri y a todos los jugadores y cuerpo técnico. Ahora y siempre, contigo #SeleccionEcuatoriana   #LaTri #ElBancodeLaTRI #ennervalencia𓃵 #EcuadorJuegaLimpio #FIFAWorldCupQatar2022 #Qatar2022 #Ecuador  https://t.co/le7iHYrMdt", "language": "es", "mentions": [{"screen_name": "latri", "name": "la tri 🇪🇨", "id": "1131208134977032193"}], "urls": [], "photos": [], "replies_count": 0, "retweets_count": 2, "likes_count": 6, "hashtags": ["seleccionecuatoriana", "latri", "elbancodelatri", "ennervalencia𓃵", "ecuadorjuegalimpio", "fifaworldcupqatar2022", "qatar2022", "ecuador"], "cashtags": [], "link": "https://twitter.com/michael_churos/status/1597772388141531137", "retweet": false, "quote_url": "", "video": 1, "thumbnail": "https://pbs.twimg.com/ext_tw_video_thumb/1597772226752831489/pu/img/8dPLR1YQwTEEBzqh.jpg", "near": "", "geo": "", "source": "", "user_rt_id": "", "user_rt": "", "retweet_id": "", "reply_to": [], "retweet_date": "", "translate": "", "trans_src": "", "trans_dest": ""}
{"id": 1597771998671011840, "conversation_id": "1597771998671011840", "created_at": "2022-11-30 02:58:24 Hora estándar romance", "date": "2022-11-30", "time": "02:58:24", "timezone": "+0100", "user_id": 1093151327516061697, "username": "estebanvillama9", "name": "Esteban Villamar🇪🇨", "place": "", "tweet": "Mientras el #Ecuador entero andaba con los ojos en el #MundialQatar2022 , el señor vidrio salió libre y el presidente #Lasso cómo responde a eso ? Creando un nuevo ministerio, y con ello más burocracia inútil. Vea señor presidente el pueblo quiere justicia, obras, no paja.", "language": "es", "mentions": [], "urls": [], "photos": [], "replies_count": 4, "retweets_count": 19, "likes_count": 32, "hashtags": ["ecuador", "mundialqatar2022", "lasso"], "cashtags": [], "link": "https://twitter.com/EstebanVillama9/status/1597771998671011840", "retweet": false, "quote_url": "", "video": 0, "thumbnail": "", "near": "", "geo": "", "source": "", "user_rt_id": "", "user_rt": "", "retweet_id": "", "reply_to": [], "retweet_date": "", "translate": "", "trans_src": "", "trans_dest": ""}
{"id": 1597771602913263616, "conversation_id": "1597771602913263616", "created_at": "2022-11-30 02:56:49 Hora estándar romance", "date": "2022-11-30", "time": "02:56:49", "timezone": "+0100", "user_id": 107241277, "username": "rmoralesverduga", "name": "Ramón Morales Verduga", "place": "", "tweet": "Vamos al aire en #ElShowDelFutbol por @goltvecu para toda #Latinoamérica. Análisis de la ELIMINACIÓN de #Ecuador en el mundial de #Qatar2022. ¿Qué te sucedió tricolor? 🇪🇨🥇⚽️🏆✅  https://t.co/dHiO8mDgaz", "language": "es", "mentions": [{"screen_name": "goltvecu", "name": "goltv ecuador", "id": "878088863130017792"}], "urls": [], "photos": ["https://pbs.twimg.com/media/FixszOCWQAAdBod.jpg"], "replies_count": 0, "retweets_count": 1, "likes_count": 10, "hashtags": ["elshowdelfutbol", "latinoamérica", "ecuador", "qatar2022"], "cashtags": [], "link": "https://twitter.com/Rmoralesverduga/status/1597771602913263616", "retweet": false, "quote_url": "", "video": 1, "thumbnail": "https://pbs.twimg.com/media/FixszOCWQAAdBod.jpg", "near": "", "geo": "", "source": "", "user_rt_id": "", "user_rt": "", "retweet_id": "", "reply_to": [], "retweet_date": "", "translate": "", "trans_src": "", "trans_dest": ""}
{"id": 1597769418364182529, "conversation_id": "1597769418364182529", "created_at": "2022-11-30 02:48:09 Hora estándar romance", "date": "2022-11-30", "time": "02:48:09", "timezone": "+0100", "user_id": 37717733, "username": "futbolecuador", "name": "futbolecuador.com", "place": "", "tweet": "“Volveremos a ver a estos muchachos. De eso no hay ninguna duda”. FIFA advierte que la Selección de #Ecuador no se quedará con la dura eliminación de #Qatar2022  https://t.co/e3DZzqwQ5n  https://t.co/6rO26QyYph", "language": "es", "mentions": [], "urls": ["http://en.fut.ec/?l=151097"], "photos": ["https://pbs.twimg.com/media/Fixq0biVIAASWlP.jpg"], "replies_count": 1, "retweets_count": 1, "likes_count": 31, "hashtags": ["ecuador", "qatar2022"], "cashtags": [], "link": "https://twitter.com/futbolecuador/status/1597769418364182529", "retweet": false, "quote_url": "", "video": 1, "thumbnail": "https://pbs.twimg.com/media/Fixq0biVIAASWlP.jpg", "near": "", "geo": "", "source": "", "user_rt_id": "", "user_rt": "", "retweet_id": "", "reply_to": [], "retweet_date": "", "translate": "", "trans_src": "", "trans_dest": ""}
{"id": 1597764443135389696, "conversation_id": "1597764443135389696", "created_at": "2022-11-30 02:28:22 Hora estándar romance", "date": "2022-11-30", "time": "02:28:22", "timezone": "+0100", "user_id": 37717733, "username": "futbolecuador", "name": "futbolecuador.com", "place": "", "tweet": "\"Orgullo de ustedes, máquinas. Siempre cabeza arriba”. Byron Castillo y un mensaje para levantar la moral de todos los jugadores de #LaTri en #Qatar2022  https://t.co/jVT9pZKuFA  https://t.co/DLiX8CUqZg", "language": "es", "mentions": [], "urls": ["http://en.fut.ec/?l=151095"], "photos": ["https://pbs.twimg.com/media/FixmS2xVUAE0mT8.jpg"], "replies_count": 4, "retweets_count": 2, "likes_count": 15, "hashtags": ["latri", "qatar2022"], "cashtags": [], "link": "https://twitter.com/futbolecuador/status/1597764443135389696", "retweet": false, "quote_url": "", "video": 1, "thumbnail": "https://pbs.twimg.com/media/FixmS2xVUAE0mT8.jpg", "near": "", "geo": "", "source": "", "user_rt_id": "", "user_rt": "", "retweet_id": "", "reply_to": [], "retweet_date": "", "translate": "", "trans_src": "", "trans_dest": ""}
{"id": 1597759448327782401, "conversation_id": "1597759448327782401", "created_at": "2022-11-30 02:08:32 Hora estándar romance", "date": "2022-11-30", "time": "02:08:32", "timezone": "+0100", "user_id": 616252147, "username": "johnreyes1983", "name": "John Jairo Reyes A.", "place": "", "tweet": "No nos deben nada @EnnerValencia14 al contrario el #Ecuador🇪🇨 queda eternamente agradecido con ustedes por habernos regalado un fantástico #MundialQatar2022.  #Viva #LaTri  #Viva #LaTri  #Viva #LaTri  #Viva #LaTri  https://t.co/RpixEC6Lj7", "language": "es", "mentions": [{"screen_name": "ennervalencia14", "name": "ennervalencia", "id": "1003023973"}], "urls": [], "photos": [], "replies_count": 0, "retweets_count": 5, "likes_count": 9, "hashtags": ["ecuador", "mundialqatar2022", "viva", "latri", "viva", "latri", "viva", "latri", "viva", "latri"], "cashtags": [], "link": "https://twitter.com/johnreyes1983/status/1597759448327782401", "retweet": false, "quote_url": "", "video": 1, "thumbnail": "https://pbs.twimg.com/ext_tw_video_thumb/1597759406170578947/pu/img/6htr0lP1nmDBtUEu.jpg", "near": "", "geo": "", "source": "", "user_rt_id": "", "user_rt": "", "retweet_id": "", "reply_to": [], "retweet_date": "", "translate": "", "trans_src": "", "trans_dest": ""}
{"id": 1597759158052614144, "conversation_id": "1597759158052614144", "created_at": "2022-11-30 02:07:22 Hora estándar romance", "date": "2022-11-30", "time": "02:07:22", "timezone": "+0100", "user_id": 324419011, "username": "ecuatosenpanama", "name": "EcuatorianosenPanamá", "place": "", "tweet": "GRACIAS  A la TRI  🇪🇨  Nos unieron a todos los ecuatorianos dentro y fuera del país en un solo grito !ECUADOR!  🇪🇨   #LaTri  #FIFAWorldCupQatar2022  #VamosEcuador #Qatar2022  #ecuatorianos  #Ecuador  #EcuatorianosenPanama @EcuaExterior  https://t.co/0fiAkCvCdI", "language": "es", "mentions": [{"screen_name": "ecuaexterior", "name": "🎙️ radio de los ecuatorianos en el exterior", "id": "1404753420439932931"}], "urls": [], "photos": ["https://pbs.twimg.com/media/FixhfK2WQAAJ4NL.jpg"], "replies_count": 0, "retweets_count": 1, "likes_count": 6, "hashtags": ["latri", "fifaworldcupqatar2022", "vamosecuador", "qatar2022", "ecuatorianos", "ecuador", "ecuatorianosenpanama"], "cashtags": [], "link": "https://twitter.com/ecuatosenpanama/status/1597759158052614144", "retweet": false, "quote_url": "", "video": 1, "thumbnail": "https://pbs.twimg.com/media/FixhfK2WQAAJ4NL.jpg", "near": "", "geo": "", "source": "", "user_rt_id": "", "user_rt": "", "retweet_id": "", "reply_to": [], "retweet_date": "", "translate": "", "trans_src": "", "trans_dest": ""}
{"id": 1597758704908046336, "conversation_id": "1597758704908046336", "created_at": "2022-11-30 02:05:34 Hora estándar romance", "date": "2022-11-30", "time": "02:05:34", "timezone": "+0100", "user_id": 1548375760259260416, "username": "taitapand4_ofc", "name": "тaιтapanda", "place": "", "tweet": "De la vida misma 🤣🤣🤣🤣 #toroc #SiSePuede #NoSePudo #ElBancodeLaTRI #LaTri #MundialQatar2022 #FIFAWorldCupQatar2022 #Ecu #EcuadorvsSenegal  https://t.co/BoLAjVV3xh", "language": "es", "mentions": [], "urls": [], "photos": [], "replies_count": 3, "retweets_count": 11, "likes_count": 24, "hashtags": ["toroc", "sisepuede", "nosepudo", "elbancodelatri", "latri", "mundialqatar2022", "fifaworldcupqatar2022", "ecu", "ecuadorvssenegal"], "cashtags": [], "link": "https://twitter.com/taitapand4_OFC/status/1597758704908046336", "retweet": false, "quote_url": "", "video": 1, "thumbnail": "https://pbs.twimg.com/ext_tw_video_thumb/1597758633248538624/pu/img/h1xbfJl5wAACSkI7.jpg", "near": "", "geo": "", "source": "", "user_rt_id": "", "user_rt": "", "retweet_id": "", "reply_to": [], "retweet_date": "", "translate": "", "trans_src": "", "trans_dest": ""}
{"id": 1597758104900276225, "conversation_id": "1597758104900276225", "created_at": "2022-11-30 02:03:11 Hora estándar romance", "date": "2022-11-30", "time": "02:03:11", "timezone": "+0100", "user_id": 68601959, "username": "darwinriofriop", "name": "𝐷𝑎𝑟𝑤𝑖𝑛 𝑅𝑖𝑜𝑓𝑟𝑖𝑜 𝑃𝑒𝑛̃𝑎 🇪🇨🇵🇱", "place": "", "tweet": "This time it was not for #Ecuador 🇪🇨😥now I will support the Polish team for all that it means to me so let's go Poland 🇵🇱 💪  #PolandVsArgentina #Poland🇵🇱 #Qatar2022 #FIFAWorldCup", "language": "en", "mentions": [], "urls": [], "photos": [], "replies_count": 1, "retweets_count": 8, "likes_count": 10, "hashtags": ["ecuador", "polandvsargentina", "poland", "qatar2022", "fifaworldcup"], "cashtags": [], "link": "https://twitter.com/DarwinRiofrioP/status/1597758104900276225", "retweet": false, "quote_url": "", "video": 0, "thumbnail": "", "near": "", "geo": "", "source": "", "user_rt_id": "", "user_rt": "", "retweet_id": "", "reply_to": [], "retweet_date": "", "translate": "", "trans_src": "", "trans_dest": ""}
{"id": 1597758045928706048, "conversation_id": "1597758045928706048", "created_at": "2022-11-30 02:02:57 Hora estándar romance", "date": "2022-11-30", "time": "02:02:57", "timezone": "+0100", "user_id": 256747696, "username": "ecuavisainforma", "name": "Ecuavisa Noticias", "place": "", "tweet": "Un hincha de #LaTri presente en #Qatar2022 compartió en sus redes sociales un emotivo momento mientras esperaba a la delegación de la 'Tricolor'.  Lee más 👉  https://t.co/NNq3xJeIv0  https://t.co/LhqrxjlggL", "language": "es", "mentions": [], "urls": ["https://bit.ly/3GWrjY5"], "photos": ["https://pbs.twimg.com/media/FixgQZ-WAAAz6eZ.jpg"], "replies_count": 2, "retweets_count": 11, "likes_count": 85, "hashtags": ["latri", "qatar2022"], "cashtags": [], "link": "https://twitter.com/EcuavisaInforma/status/1597758045928706048", "retweet": false, "quote_url": "", "video": 1, "thumbnail": "https://pbs.twimg.com/media/FixgQZ-WAAAz6eZ.jpg", "near": "", "geo": "", "source": "", "user_rt_id": "", "user_rt": "", "retweet_id": "", "reply_to": [], "retweet_date": "", "translate": "", "trans_src": "", "trans_dest": ""}
{"id": 1597751010222428160, "conversation_id": "1597751010222428160", "created_at": "2022-11-30 01:35:00 Hora estándar romance", "date": "2022-11-30", "time": "01:35:00", "timezone": "+0100", "user_id": 761111202541948928, "username": "france24_es", "name": "FRANCE 24 Español", "place": "", "tweet": "⚽🏆 #Ecuador se convirtió en el primer equipo latinoamericano en quedarse por fuera del Mundial de #Qatar2022 ➡️  https://t.co/hxf9tEcAPs   🎙 @jdpupiales  #QatarWorldCup2022 #FIFAWorldCup  https://t.co/Z3SuvAbCUj", "language": "es", "mentions": [{"screen_name": "jdpupiales", "name": "juan pupiales", "id": "494244543"}], "urls": ["https://f24.my/94mj.t"], "photos": [], "replies_count": 1, "retweets_count": 5, "likes_count": 11, "hashtags": ["ecuador", "qatar2022", "qatarworldcup2022", "fifaworldcup"], "cashtags": [], "link": "https://twitter.com/France24_es/status/1597751010222428160", "retweet": false, "quote_url": "", "video": 1, "thumbnail": "https://pbs.twimg.com/media/FixLM2SUAAAF6j6.jpg", "near": "", "geo": "", "source": "", "user_rt_id": "", "user_rt": "", "retweet_id": "", "reply_to": [], "retweet_date": "", "translate": "", "trans_src": "", "trans_dest": ""}
{"id": 1597747152922742785, "conversation_id": "1597747152922742785", "created_at": "2022-11-30 01:19:40 Hora estándar romance", "date": "2022-11-30", "time": "01:19:40", "timezone": "+0100", "user_id": 189124591, "username": "avastudillo", "name": "Alberto Astudillo B.", "place": "", "tweet": "Alemania 🇩🇪 2006 sigue siendo la mejor presentación de @LaTri en mundiales. En Stuttgart siguen retumbando algunos nombres que seguirán impulsando a jugadores actuales y futuras estrellas de #Ecuador ⚽️ en el fútbol mundial. #Qatar2022  https://t.co/rhat5ae4fu", "language": "es", "mentions": [{"screen_name": "latri", "name": "la tri 🇪🇨", "id": "1131208134977032193"}], "urls": [], "photos": ["https://pbs.twimg.com/media/FixWjwhWYAALtgc.jpg", "https://pbs.twimg.com/media/FixWjukXkAI7s9Y.jpg"], "replies_count": 2, "retweets_count": 1, "likes_count": 15, "hashtags": ["ecuador", "qatar2022"], "cashtags": [], "link": "https://twitter.com/AVAstudillo/status/1597747152922742785", "retweet": false, "quote_url": "https://twitter.com/avastudillo/status/1597636154152869888", "video": 1, "thumbnail": "https://pbs.twimg.com/media/FixWjwhWYAALtgc.jpg", "near": "", "geo": "", "source": "", "user_rt_id": "", "user_rt": "", "retweet_id": "", "reply_to": [], "retweet_date": "", "translate": "", "trans_src": "", "trans_dest": ""}
{"id": 1597745102491115520, "conversation_id": "1597745102491115520", "created_at": "2022-11-30 01:11:31 Hora estándar romance", "date": "2022-11-30", "time": "01:11:31", "timezone": "+0100", "user_id": 135628351, "username": "martinguzmantf", "name": "Martín Guzmán", "place": "", "tweet": "Hay futuro: No le deben nada a nadie. #Ecuador hizo un gran mundial, pero se quedó fuera de #Qatar2022. Mi criterio sobre la participación de #LaTri en la Copa del Mundo, para @TercerFutbol. ⬇️  https://t.co/kqwgcd08Un", "language": "es", "mentions": [{"screen_name": "tercerfutbol", "name": "tercer fútbol", "id": "800440622230302720"}], "urls": ["https://bit.ly/3XKNBSu"], "photos": [], "replies_count": 0, "retweets_count": 2, "likes_count": 5, "hashtags": ["ecuador", "qatar2022", "latri"], "cashtags": [], "link": "https://twitter.com/MartinGuzmanTF/status/1597745102491115520", "retweet": false, "quote_url": "", "video": 0, "thumbnail": "", "near": "", "geo": "", "source": "", "user_rt_id": "", "user_rt": "", "retweet_id": "", "reply_to": [], "retweet_date": "", "translate": "", "trans_src": "", "trans_dest": ""}
{"id": 1597743189280313345, "conversation_id": "1597743189280313345", "created_at": "2022-11-30 01:03:55 Hora estándar romance", "date": "2022-11-30", "time": "01:03:55", "timezone": "+0100", "user_id": 1283071396667707399, "username": "vallejojoseph25", "name": "Joseph Vallejo Aguirre", "place": "", "tweet": "Con cabeza más fría puedo sacar ya muchas conclusiones: #Ecuador tuvo en #Qatar2022 una clasificación a este torneo con demasiadas interrogantes porque aunque no lo dábamos a notar sentíamos que no podíamos celebrar o estar tranquilos por el tema legal que tenía Byron Castillo...", "language": "es", "mentions": [], "urls": [], "photos": [], "replies_count": 1, "retweets_count": 1, "likes_count": 7, "hashtags": ["ecuador", "qatar2022"], "cashtags": [], "link": "https://twitter.com/VallejoJoseph25/status/1597743189280313345", "retweet": false, "quote_url": "", "video": 0, "thumbnail": "", "near": "", "geo": "", "source": "", "user_rt_id": "", "user_rt": "", "retweet_id": "", "reply_to": [], "retweet_date": "", "translate": "", "trans_src": "", "trans_dest": ""}
{"id": 1597743157000933376, "conversation_id": "1597743157000933376", "created_at": "2022-11-30 01:03:47 Hora estándar romance", "date": "2022-11-30", "time": "01:03:47", "timezone": "+0100", "user_id": 1143686680513306624, "username": "ismaelulloaec", "name": "Ismael Ulloa", "place": "", "tweet": "⚽️ Los “periodistas y analistas” futbolísticos que más le dan con todo a la #LaTri , son los que no consiguieron quién les auspicie la ida a #Qatar2022 .  JAJAJAJAJAJAJAJAJAJAJA  El resto son los/as giles que viven refundidos en ese asquito del “amor por lo colores” de cada club.", "language": "es", "mentions": [], "urls": [], "photos": [], "replies_count": 0, "retweets_count": 9, "likes_count": 49, "hashtags": ["latri", "qatar2022"], "cashtags": [], "link": "https://twitter.com/IsmaelUlloaEc/status/1597743157000933376", "retweet": false, "quote_url": "", "video": 0, "thumbnail": "", "near": "", "geo": "", "source": "", "user_rt_id": "", "user_rt": "", "retweet_id": "", "reply_to": [], "retweet_date": "", "translate": "", "trans_src": "", "trans_dest": ""}
{"id": 1597742207535939584, "conversation_id": "1597742207535939584", "created_at": "2022-11-30 01:00:01 Hora estándar romance", "date": "2022-11-30", "time": "01:00:01", "timezone": "+0100", "user_id": 105186569, "username": "studiofutbol", "name": "StudioFútbol ⚽", "place": "", "tweet": "Las lágrimas de los jugadores de #Ecuador tras quedar eliminados (VIDEO)  https://t.co/KpEAh1Q9TP #Qatar2022", "language": "es", "mentions": [], "urls": ["http://bit.ly/3OPiQbk"], "photos": [], "replies_count": 0, "retweets_count": 3, "likes_count": 9, "hashtags": ["ecuador", "qatar2022"], "cashtags": [], "link": "https://twitter.com/StudioFutbol/status/1597742207535939584", "retweet": false, "quote_url": "", "video": 0, "thumbnail": "", "near": "", "geo": "", "source": "", "user_rt_id": "", "user_rt": "", "retweet_id": "", "reply_to": [], "retweet_date": "", "translate": "", "trans_src": "", "trans_dest": ""}
