{"id": 1603454921768157185, "conversation_id": "1603454921768157185", "created_at": "2022-12-15 19:20:18 Hora estándar romance", "date": "2022-12-15", "time": "19:20:18", "timezone": "+0100", "user_id": 3306315704, "username": "elfinancierotv", "name": "El Financiero TV", "place": "", "tweet": "#EFMeetPointVirtual | Países como #Alemania #Argentina o #Francia siguen procesos; 'en #México es muy difícil ver que un técnico dure 8 años; hay que aprender de los que hacen bien las cosas sin importar tropiezos': @fersch_4 tras el fracaso de la #SelecciónMexicana en #Qatar2022  https://t.co/HPDZn1rCIr", "language": "es", "mentions": [{"screen_name": "fersch_4", "name": "fernando schwartz #nuncabajolosbrazos", "id": "27954537"}], "urls": [], "photos": [], "replies_count": 0, "retweets_count": 3, "likes_count": 9, "hashtags": ["efmeetpointvirtual", "alemania", "argentina", "francia", "méxico", "selecciónmexicana", "qatar2022"], "cashtags": [], "link": "https://twitter.com/ElFinancieroTv/status/1603454921768157185", "retweet": false, "quote_url": "", "video": 1, "thumbnail": "https://pbs.twimg.com/amplify_video_thumb/1603452626099916800/img/fEjFFBTFkllrGzzt.jpg", "near": "", "geo": "", "source": "", "user_rt_id": "", "user_rt": "", "retweet_id": "", "reply_to": [], "retweet_date": "", "translate": "", "trans_src": "", "trans_dest": ""}
