{"id": 1603411686354210819, "conversation_id": "1603411686354210819", "created_at": "2022-12-15 16:28:30 Hora estándar romance", "date": "2022-12-15", "time": "16:28:30", "timezone": "+0100", "user_id": 1178636242835181568, "username": "unitylinkltd", "name": "UnityLink Financial Services Ltd", "place": "", "tweet": "Congratulations to all winners.  Kindly get in touch via DM to redeem your rewards. #rewards #unitylink #moneytransfer #Ghana #worldcup2022  https://t.co/hrv2rfRcLD", "language": "en", "mentions": [], "urls": [], "photos": ["https://pbs.twimg.com/media/FkB2bIXXkAEpqUx.jpg", "https://pbs.twimg.com/media/FkB2bIVXgAEsoy7.jpg"], "replies_count": 4, "retweets_count": 3, "likes_count": 12, "hashtags": ["rewards", "unitylink", "moneytransfer", "ghana", "worldcup2022"], "cashtags": [], "link": "https://twitter.com/UnitylinkLtd/status/1603411686354210819", "retweet": false, "quote_url": "", "video": 1, "thumbnail": "https://pbs.twimg.com/media/FkB2bIXXkAEpqUx.jpg", "near": "", "geo": "", "source": "", "user_rt_id": "", "user_rt": "", "retweet_id": "", "reply_to": [], "retweet_date": "", "translate": "", "trans_src": "", "trans_dest": ""}
